package com.project.library.core;

import android.os.Binder;
import android.os.IBinder;
import android.os.IInterface;
import android.os.Parcel;
import android.os.RemoteException;

public abstract interface ICoreService
  extends IInterface
{
  public abstract boolean connect(String paramString)
    throws RemoteException;
  
  public abstract boolean disconnect()
    throws RemoteException;
  
  public abstract boolean initBLE(byte paramByte)
    throws RemoteException;
  
  public abstract boolean isDeviceConnected()
    throws RemoteException;
  
  public abstract void registerCallback(ICoreServiceCallback paramICoreServiceCallback)
    throws RemoteException;
  
  public abstract void unregisterCallback(ICoreServiceCallback paramICoreServiceCallback)
    throws RemoteException;
  
  public abstract boolean write(byte[] paramArrayOfByte)
    throws RemoteException;
  
  public abstract boolean writeForce(byte[] paramArrayOfByte)
    throws RemoteException;
  
  public static abstract class Stub
    extends Binder
    implements ICoreService
  {
    private static final String DESCRIPTOR = "com.project.library.core.ICoreService";
    static final int TRANSACTION_connect = 4;
    static final int TRANSACTION_disconnect = 5;
    static final int TRANSACTION_initBLE = 3;
    static final int TRANSACTION_isDeviceConnected = 8;
    static final int TRANSACTION_registerCallback = 1;
    static final int TRANSACTION_unregisterCallback = 2;
    static final int TRANSACTION_write = 6;
    static final int TRANSACTION_writeForce = 7;
    
    public Stub()
    {
      attachInterface(this, "com.project.library.core.ICoreService");
    }
    
    public static ICoreService asInterface(IBinder paramIBinder)
    {
      if (paramIBinder == null) {
        return null;
      }
      IInterface localIInterface = paramIBinder.queryLocalInterface("com.project.library.core.ICoreService");
      if ((localIInterface != null) && ((localIInterface instanceof ICoreService))) {
        return (ICoreService)localIInterface;
      }
      return new Proxy(paramIBinder);
    }
    
    public IBinder asBinder()
    {
      return this;
    }
    
    public boolean onTransact(int paramInt1, Parcel paramParcel1, Parcel paramParcel2, int paramInt2)
      throws RemoteException
    {
      int j = 0;
      int k = 0;
      int m = 0;
      int n = 0;
      int i1 = 0;
      int i = 0;
      switch (paramInt1)
      {
      default: 
        return super.onTransact(paramInt1, paramParcel1, paramParcel2, paramInt2);
      case 1598968902: 
        paramParcel2.writeString("com.project.library.core.ICoreService");
        return true;
      case 1: 
        paramParcel1.enforceInterface("com.project.library.core.ICoreService");
        registerCallback(ICoreServiceCallback.Stub.asInterface(paramParcel1.readStrongBinder()));
        paramParcel2.writeNoException();
        return true;
      case 2: 
        paramParcel1.enforceInterface("com.project.library.core.ICoreService");
        unregisterCallback(ICoreServiceCallback.Stub.asInterface(paramParcel1.readStrongBinder()));
        paramParcel2.writeNoException();
        return true;
      case 3: 
        paramParcel1.enforceInterface("com.project.library.core.ICoreService");
        bool = initBLE(paramParcel1.readByte());
        paramParcel2.writeNoException();
        paramInt1 = i;
        if (bool) {
          paramInt1 = 1;
        }
        paramParcel2.writeInt(paramInt1);
        return true;
      case 4: 
        paramParcel1.enforceInterface("com.project.library.core.ICoreService");
        bool = connect(paramParcel1.readString());
        paramParcel2.writeNoException();
        paramInt1 = j;
        if (bool) {
          paramInt1 = 1;
        }
        paramParcel2.writeInt(paramInt1);
        return true;
      case 5: 
        paramParcel1.enforceInterface("com.project.library.core.ICoreService");
        bool = disconnect();
        paramParcel2.writeNoException();
        paramInt1 = k;
        if (bool) {
          paramInt1 = 1;
        }
        paramParcel2.writeInt(paramInt1);
        return true;
      case 6: 
        paramParcel1.enforceInterface("com.project.library.core.ICoreService");
        bool = write(paramParcel1.createByteArray());
        paramParcel2.writeNoException();
        paramInt1 = m;
        if (bool) {
          paramInt1 = 1;
        }
        paramParcel2.writeInt(paramInt1);
        return true;
      case 7: 
        paramParcel1.enforceInterface("com.project.library.core.ICoreService");
        bool = writeForce(paramParcel1.createByteArray());
        paramParcel2.writeNoException();
        paramInt1 = n;
        if (bool) {
          paramInt1 = 1;
        }
        paramParcel2.writeInt(paramInt1);
        return true;
      }
      paramParcel1.enforceInterface("com.project.library.core.ICoreService");
      boolean bool = isDeviceConnected();
      paramParcel2.writeNoException();
      paramInt1 = i1;
      if (bool) {
        paramInt1 = 1;
      }
      paramParcel2.writeInt(paramInt1);
      return true;
    }
    
    private static class Proxy
      implements ICoreService
    {
      private IBinder mRemote;
      
      Proxy(IBinder paramIBinder)
      {
        this.mRemote = paramIBinder;
      }
      
      public IBinder asBinder()
      {
        return this.mRemote;
      }
      
      public boolean connect(String paramString)
        throws RemoteException
      {
        boolean bool = false;
        Parcel localParcel1 = Parcel.obtain();
        Parcel localParcel2 = Parcel.obtain();
        try
        {
          localParcel1.writeInterfaceToken("com.project.library.core.ICoreService");
          localParcel1.writeString(paramString);
          this.mRemote.transact(4, localParcel1, localParcel2, 0);
          localParcel2.readException();
          int i = localParcel2.readInt();
          if (i != 0) {
            bool = true;
          }
          return bool;
        }
        finally
        {
          localParcel2.recycle();
          localParcel1.recycle();
        }
      }
      
      public boolean disconnect()
        throws RemoteException
      {
        boolean bool = false;
        Parcel localParcel1 = Parcel.obtain();
        Parcel localParcel2 = Parcel.obtain();
        try
        {
          localParcel1.writeInterfaceToken("com.project.library.core.ICoreService");
          this.mRemote.transact(5, localParcel1, localParcel2, 0);
          localParcel2.readException();
          int i = localParcel2.readInt();
          if (i != 0) {
            bool = true;
          }
          return bool;
        }
        finally
        {
          localParcel2.recycle();
          localParcel1.recycle();
        }
      }
      
      public String getInterfaceDescriptor()
      {
        return "com.project.library.core.ICoreService";
      }
      
      public boolean initBLE(byte paramByte)
        throws RemoteException
      {
        boolean bool = false;
        Parcel localParcel1 = Parcel.obtain();
        Parcel localParcel2 = Parcel.obtain();
        try
        {
          localParcel1.writeInterfaceToken("com.project.library.core.ICoreService");
          localParcel1.writeByte(paramByte);
          this.mRemote.transact(3, localParcel1, localParcel2, 0);
          localParcel2.readException();
          int i = localParcel2.readInt();
          if (i != 0) {
            bool = true;
          }
          return bool;
        }
        finally
        {
          localParcel2.recycle();
          localParcel1.recycle();
        }
      }
      
      public boolean isDeviceConnected()
        throws RemoteException
      {
        boolean bool = false;
        Parcel localParcel1 = Parcel.obtain();
        Parcel localParcel2 = Parcel.obtain();
        try
        {
          localParcel1.writeInterfaceToken("com.project.library.core.ICoreService");
          this.mRemote.transact(8, localParcel1, localParcel2, 0);
          localParcel2.readException();
          int i = localParcel2.readInt();
          if (i != 0) {
            bool = true;
          }
          return bool;
        }
        finally
        {
          localParcel2.recycle();
          localParcel1.recycle();
        }
      }
      
      /* Error */
      public void registerCallback(ICoreServiceCallback paramICoreServiceCallback)
        throws RemoteException
      {
        // Byte code:
        //   0: invokestatic 32	android/os/Parcel:obtain	()Landroid/os/Parcel;
        //   3: astore_2
        //   4: invokestatic 32	android/os/Parcel:obtain	()Landroid/os/Parcel;
        //   7: astore_3
        //   8: aload_2
        //   9: ldc 34
        //   11: invokevirtual 38	android/os/Parcel:writeInterfaceToken	(Ljava/lang/String;)V
        //   14: aload_1
        //   15: ifnull +42 -> 57
        //   18: aload_1
        //   19: invokeinterface 75 1 0
        //   24: astore_1
        //   25: aload_2
        //   26: aload_1
        //   27: invokevirtual 78	android/os/Parcel:writeStrongBinder	(Landroid/os/IBinder;)V
        //   30: aload_0
        //   31: getfield 19	com/project/library/core/ICoreService$Stub$Proxy:mRemote	Landroid/os/IBinder;
        //   34: iconst_1
        //   35: aload_2
        //   36: aload_3
        //   37: iconst_0
        //   38: invokeinterface 47 5 0
        //   43: pop
        //   44: aload_3
        //   45: invokevirtual 50	android/os/Parcel:readException	()V
        //   48: aload_3
        //   49: invokevirtual 57	android/os/Parcel:recycle	()V
        //   52: aload_2
        //   53: invokevirtual 57	android/os/Parcel:recycle	()V
        //   56: return
        //   57: aconst_null
        //   58: astore_1
        //   59: goto -34 -> 25
        //   62: astore_1
        //   63: aload_3
        //   64: invokevirtual 57	android/os/Parcel:recycle	()V
        //   67: aload_2
        //   68: invokevirtual 57	android/os/Parcel:recycle	()V
        //   71: aload_1
        //   72: athrow
        // Local variable table:
        //   start	length	slot	name	signature
        //   0	73	0	this	Proxy
        //   0	73	1	paramICoreServiceCallback	ICoreServiceCallback
        //   3	65	2	localParcel1	Parcel
        //   7	57	3	localParcel2	Parcel
        // Exception table:
        //   from	to	target	type
        //   8	14	62	finally
        //   18	25	62	finally
        //   25	48	62	finally
      }
      
      /* Error */
      public void unregisterCallback(ICoreServiceCallback paramICoreServiceCallback)
        throws RemoteException
      {
        // Byte code:
        //   0: invokestatic 32	android/os/Parcel:obtain	()Landroid/os/Parcel;
        //   3: astore_2
        //   4: invokestatic 32	android/os/Parcel:obtain	()Landroid/os/Parcel;
        //   7: astore_3
        //   8: aload_2
        //   9: ldc 34
        //   11: invokevirtual 38	android/os/Parcel:writeInterfaceToken	(Ljava/lang/String;)V
        //   14: aload_1
        //   15: ifnull +42 -> 57
        //   18: aload_1
        //   19: invokeinterface 75 1 0
        //   24: astore_1
        //   25: aload_2
        //   26: aload_1
        //   27: invokevirtual 78	android/os/Parcel:writeStrongBinder	(Landroid/os/IBinder;)V
        //   30: aload_0
        //   31: getfield 19	com/project/library/core/ICoreService$Stub$Proxy:mRemote	Landroid/os/IBinder;
        //   34: iconst_2
        //   35: aload_2
        //   36: aload_3
        //   37: iconst_0
        //   38: invokeinterface 47 5 0
        //   43: pop
        //   44: aload_3
        //   45: invokevirtual 50	android/os/Parcel:readException	()V
        //   48: aload_3
        //   49: invokevirtual 57	android/os/Parcel:recycle	()V
        //   52: aload_2
        //   53: invokevirtual 57	android/os/Parcel:recycle	()V
        //   56: return
        //   57: aconst_null
        //   58: astore_1
        //   59: goto -34 -> 25
        //   62: astore_1
        //   63: aload_3
        //   64: invokevirtual 57	android/os/Parcel:recycle	()V
        //   67: aload_2
        //   68: invokevirtual 57	android/os/Parcel:recycle	()V
        //   71: aload_1
        //   72: athrow
        // Local variable table:
        //   start	length	slot	name	signature
        //   0	73	0	this	Proxy
        //   0	73	1	paramICoreServiceCallback	ICoreServiceCallback
        //   3	65	2	localParcel1	Parcel
        //   7	57	3	localParcel2	Parcel
        // Exception table:
        //   from	to	target	type
        //   8	14	62	finally
        //   18	25	62	finally
        //   25	48	62	finally
      }
      
      public boolean write(byte[] paramArrayOfByte)
        throws RemoteException
      {
        boolean bool = false;
        Parcel localParcel1 = Parcel.obtain();
        Parcel localParcel2 = Parcel.obtain();
        try
        {
          localParcel1.writeInterfaceToken("com.project.library.core.ICoreService");
          localParcel1.writeByteArray(paramArrayOfByte);
          this.mRemote.transact(6, localParcel1, localParcel2, 0);
          localParcel2.readException();
          int i = localParcel2.readInt();
          if (i != 0) {
            bool = true;
          }
          return bool;
        }
        finally
        {
          localParcel2.recycle();
          localParcel1.recycle();
        }
      }
      
      public boolean writeForce(byte[] paramArrayOfByte)
        throws RemoteException
      {
        boolean bool = false;
        Parcel localParcel1 = Parcel.obtain();
        Parcel localParcel2 = Parcel.obtain();
        try
        {
          localParcel1.writeInterfaceToken("com.project.library.core.ICoreService");
          localParcel1.writeByteArray(paramArrayOfByte);
          this.mRemote.transact(7, localParcel1, localParcel2, 0);
          localParcel2.readException();
          int i = localParcel2.readInt();
          if (i != 0) {
            bool = true;
          }
          return bool;
        }
        finally
        {
          localParcel2.recycle();
          localParcel1.recycle();
        }
      }
    }
  }
}


/* Location:              C:\Users\julian\Downloads\Veryfit 2 0_vV2.0.28_apkpure.com-dex2jar.jar!\com\project\library\core\ICoreService.class
 * Java compiler version: 6 (50.0)
 * JD-Core Version:       0.7.1
 */